Workbook
Name __________vv594: [1]Grouping!#REF!
Name ________vv594: [2]Grouping!#REF!
Name _______vv594: [2]Grouping!#REF!
Name ______vv594: [2]Grouping!#REF!
Name _____vv594: [2]Grouping!#REF!
Name ____vv594: [2]Grouping!#REF!
Name ___vv594: [2]Grouping!#REF!
Name __vv594: [3]Grouping!#REF!
Name _vv594: [2]Grouping!#REF!
Name aaa: #REF!
Name concurrent: #REF!
Name Cost_Center: #REF!
Name csDesignMode: 1
Name Date_of_CD_ROM: #REF!
Name mmm: #REF!
Name New: #REF!
Name newco: #REF!
Name noncomp: #REF!
Name qryAdjustTblFinalDataYEBalances: #REF!
Name qryClientFinancialsNoAdjustment: #REF!
Name qrytblFinalDataYEBalances: #REF!
Name SPWS_WBID: "37351C02-715D-11D3-803D-0020AFFAFC38"
Name Ticker: ""
Name Tolerance: 0.0025
Name vvv: #REF!
Name WCA: #REF!
Name we: #REF!
Name xx: #REF!
Name xxx: #REF!

Sheet Summary of Margins
A1: Annexure 5 - Unadjusted margin summary of comparable companies - Software Distribution
A2: S.No. | B2: Name of the company | C2: Year wise Gross profits/ sales (%) | F2: Weighted average of Gross profits on sales (%)
C3: FY 2024-25 | D3: FY 2023-24 | E3: FY 2022-23
A4: 1 | B4: Datasoft Network Solutions Private Limited | C4: NA | D4: ='Gross Margins'!F20 -> 0.0034582592 | E4: ='Gross Margins'!G20 -> 0.0042030406 | F4: ='Gross Margins'!E22 -> 0.31223599
A5: 2 | B5: Avance Technologies Limited | C5: NA | D5: ='Gross Margins'!AA20 -> -0.00018761916 | E5: ='Gross Margins'!AB20 -> 0.024708503 | F5: ='Gross Margins'!Z22 -> 0.0074272725
A6: 3 | B6: Perfect Computer Solutions Private Limited | C6: NA | D6: ='Gross Margins'!AG20 -> 0.016850295 | E6: ='Gross Margins'!AH20 -> 0.033880208 | F6: ='Gross Margins'!AF22 -> 0.024894101
A7: 4 | B7: Iris Global Services Private Limited | C7: NA | D7: ='Gross Margins'!AD20 -> 0.042001997 | E7: ='Gross Margins'!AE20 -> 0.040525916 | F7: ='Gross Margins'!AC22 -> 0.041364369
A8: 5 | B8: Sonata Information Technology Limited | C8: NA | D8: ='Gross Margins'!R20 -> 0.04409618 | E8: ='Gross Margins'!S20 -> 0.040585146 | F8: ='Gross Margins'!Q22 -> 0.04240355
A9: 6 | B9: Softcell Technologies Global Private Limited | C9: NA | D9: ='Gross Margins'!U20 -> 0.069194556 | E9: ='Gross Margins'!V20 -> 0.055229275 | F9: ='Gross Margins'!T22 -> 0.062399181
A10: 7 | B10: Galaxy Office Automation Private Limited | C10: NA | D10: ='Gross Margins'!I20 -> 0.07652366 | E10: ='Gross Margins'!J20 -> 0.058410958 | F10: ='Gross Margins'!H22 -> 0.066851697
A11: 8 | B11: Team Computers Private Limited | C11: NA | D11: ='Gross Margins'!X20 -> 0.1039886 | E11: ='Gross Margins'!Y20 -> 0.081692093 | F11: ='Gross Margins'!W22 -> 0.091426048
A12: 9 | B12: Informatics Technologies Private Limited | C12: NA | D12: ='Gross Margins'!L20 -> 0.13795373 | E12: ='Gross Margins'!M20 -> 0.094675019 | F12: ='Gross Margins'!K22 -> 0.10965111
A13: 10 | B13: Astute Systems Private Limited | C13: NA | D13: ='Gross Margins'!C20 -> 0.1218194 | E13: ='Gross Margins'!D20 -> 0.14029394 | F13: ='Gross Margins'!B22 -> 0.13353124
A14: 11 | B14: NTT India Private Limited | C14: NA | D14: ='Gross Margins'!O20 -> 0.14694924 | E14: ='Gross Margins'!P20 -> 0.1125781 | F14: ='Gross Margins'!N22 -> 0.13219929
A15: Arm's Length Range | E15: Data Place | F15: GP/Sales (%)
A16: 35th Percentile | E16: =ROUNDUP(A14*0.35,0) -> 4 | F16: =VLOOKUP(E16,$A$4:$F$14,6,0) -> 0.041364369
A17: Median | F17: =MEDIAN(F4:F14) -> 0.066851697
A18: 65th Percentile | E18: =ROUNDUP(A14*0.65,0) -> 8 | F18: =VLOOKUP(E18,$A$4:$F$14,6,0) -> 0.091426048
A20: Note 1: Weighted average of the margin for FY 2024-25, FY 2023-24 and FY 2022-23 has been computed using sales of the respective years being used as weights.
A21: NA denotes Not Available

Sheet Gross Margins
A2: Software Distribution - RPM - Detailed computation
A4: RPM Analysis of Comparable Companies | B4: Astute Systems Private Limited | E4: Datasoft Network Solutions Private Limited | H4: Galaxy Office Automation Private Limited | K4: Informatics Technologies Private Limited | N4: NTT India Private Limited | Q4: Sonata Information Technology Limited | T4: Softcell Technologies Global Private Limited | W4: Team Computers Private Limited | Z4: Avance Technologies Limited | AC4: Iris Global Services Private Limited | AF4: Perfect Computer Solutions Private Limited
B6: FY 2025 | C6: FY 2024 | D6: FY 2023 | E6: FY 2025 | F6: FY 2024 | G6: FY 2023 | H6: FY 2025 | I6: FY 2024 | J6: FY 2023 | K6: FY 2025 | L6: FY 2024 | M6: FY 2023 | N6: FY 2025 | O6: FY 2024 | P6: FY 2023 | Q6: FY 2025 | R6: FY 2024 | S6: FY 2023 | T6: FY 2025 | U6: FY 2024 | V6: FY 2023 | W6: FY 2025 | X6: FY 2024 | Y6: FY 2023 | Z6: FY 2025 | AA6: FY 2024 | AB6: FY 2023 | AC6: FY 2025 | AD6: FY 2024 | AE6: FY 2023 | AF6: FY 2025 | AG6: FY 2024 | AH6: FY 2023
A8: Sales | B8: =101825*1000 -> 101825000 | C8: =89876*1000 -> 89876000 | D8: =104312.42*1000 -> 104312420 | E8: =834495.4*1000 -> 834495400 | F8: =889556.51*1000 -> 889556510 | G8: =648630189 -> 648630189 | I8: 7129712280 | J8: =81697*10^5 -> 8169700000 | K8: NA | L8: =2096.5*10^5 -> 209650000 | M8: =396208*1000 -> 396208000 | N8: NA | O8: =131787*10^5 -> 13178700000 | P8: =99069*10^5 -> 9906900000 | Q8: NA | R8: =594632*10^5 -> 59463200000 | S8: =553503*10^5 -> 55350300000 | T8: NA | U8: =82324.54*10^5 -> 8.232454e+09 | V8: =78024.2*10^5 -> 7802420000 | W8: NA | X8: =192925.29*10^5 -> 19292529000 | Y8: =248987.5*10^5 -> 24898750000 | Z8: NA | AA8: =6928.93*10^5 -> 692893000 | AB8: =3053.2*10^5 -> 305320000 | AC8: NA | AD8: 27061588689 | AE8: 20579834678 | AF8: NA | AG8: 726311987 | AH8: =6501495*100 -> 650149500
A10: Cost of goods sold | B10: =B12+B14-B16 -> 87881000 | C10: =C12+C14-C16 -> 78927360 | D10: =D12+D14-D16 -> 89678020 | E10: =E12+E16-E14 -> 99461190 | F10: =F12+F14-F16 -> 886480193 | G10: =G12+G14-G16 -> 645903970 | I10: =I12+I14-I16 -> 6584120604 | J10: =J12+J14-J16 -> 7692500000 | L10: =L12+L14-L16 -> 180728000 | M10: =M12+M14-M16 -> 358697000 | O10: =O12+O14-O16 -> 11242100000 | P10: =P12+P14-P16 -> 8791600000 | R10: =R12+R14-R16 -> 56841100000 | S10: =S12+S14-S16 -> 53103900000 | U10: =U12+U14-U16 -> 7662813000 | V10: =V12+V14-V16 -> 7371498000 | X10: =X12+X14-X16 -> 17286326000 | Y10: =Y12+Y14-Y16 -> 22864719000 | AA10: =AA12+AA14-AA16 -> 693023000 | AB10: =AB12+AB14-AB16 -> 297776000 | AD10: =AD12+AD14-AD16 -> 25924947914 | AE10: =AE12+AE14-AE16 -> 19745818019 | AG10: =AG12+AG14-AG16 -> 714073416 | AH10: =AH12+AH14-AH16 -> 628122300
A12: - Opening Stock | B12: =1404*1000 -> 1404000 | C12: =2295.36*1000 -> 2295360 | D12: =2891.41*1000 -> 2891410 | E12: =428624.56*1000 -> 428624560 | F12: 226563163 | G12: 68136809 | I12: =888.07303*10^5 -> 88807303 | J12: =1465*10^5 -> 146500000 | L12: =1958*10^3 -> 1958000 | M12: =5238*1000 -> 5238000 | O12: =6291*10^5 -> 629100000 | P12: =7072*10^5 -> 707200000 | R12: =2882*10^5 -> 288200000 | S12: =276*10^5 -> 27600000 | U12: =1188.3*10^5 -> 118830000 | V12: =703.03*10^5 -> 70303000 | X12: =3153.14*10^5 -> 315314000 | Y12: =4075.96*10^5 -> 407596000 | AA12: =658.64*10^5 -> 65864000 | AB12: =377.53*10^5 -> 37753000 | AD12: 394705297 | AE12: 384656747 | AG12: =1071607.36*100 -> 1.0716074e+08 | AH12: =796534*100 -> 79653400
A14: - Purchases | B14: =87562*1000 -> 87562000 | C14: =78036*1000 -> 78036000 | D14: =89081.97*1000 -> 89081970 | E14: =458259.62*1000 -> 458259620 | F14: =1088541.59*1000 -> 1088541590 | G14: 804330324 | I14: 6724543473 | J14: =76348*10^5 -> 7634800000 | L14: =1828.5*10^5 -> 182850000 | M14: =355417*10^3 -> 355417000 | O14: =109488*10^5 -> 10948800000 | P14: =87135*10^5 -> 8713500000 | R14: =575330*10^5 -> 57533000000 | S14: =533645*10^5 -> 53364500000 | U14: =76200.81*10^5 -> 7620081000 | V14: =74200.25*10^5 -> 7420025000 | X14: =173192.9*10^5 -> 17319290000 | Y14: =227724.37*10^5 -> 22772437000 | AA14: =6271.59*10^5 -> 627159000 | AB14: =3258.87*10^5 -> 325887000 | AD14: 26213205771 | AE14: 19755866569 | AG14: 731899589 | AH14: =6556296*100 -> 655629600
A16: - Closing Stock | B16: =1085*1000 -> 1085000 | C16: =1404*1000 -> 1404000 | D16: =2295.36*1000 -> 2295360 | E16: =129096.25*1000 -> 129096250 | F16: =428624.56*1000 -> 428624560 | G16: 226563163 | I16: 229230172 | J16: =888*10^5 -> 88800000 | L16: =40.8*10^5 -> 4080000 | M16: =1958*10^3 -> 1958000 | O16: =3358*10^5 -> 335800000 | P16: =6291*10^5 -> 629100000 | R16: =9801*10^5 -> 980100000 | S16: =2882*10^5 -> 288200000 | U16: =760.98*10^5 -> 76098000 | V16: =1188.3*10^5 -> 118830000 | X16: =3482.78*10^5 -> 348278000 | Y16: =3153.14*10^5 -> 315314000 | AA16: 0 | AB16: =658.64*10^5 -> 65864000 | AD16: 682963154 | AE16: 394705297 | AG16: 124986909 | AH16: =1071607*100 -> 107160700
A18: Gross Profit | B18: =B8-B10 -> 13944000 | C18: =C8-C10 -> 10948640 | D18: =D8-D10 -> 14634400 | E18: =E8-E10 -> 735034210 | F18: =F8-F10 -> 3076317 | G18: =G8-G10 -> 2726219 | I18: =I8-I10 -> 545591676 | J18: =J8-J10 -> 477200000 | L18: =L8-L10 -> 28922000 | M18: =M8-M10 -> 37511000 | O18: =O8-O10 -> 1936600000 | P18: =P8-P10 -> 1115300000 | R18: =R8-R10 -> 2622100000 | S18: =S8-S10 -> 2246400000 | U18: =U8-U10 -> 5.69641e+08 | V18: =V8-V10 -> 430922000 | X18: =X8-X10 -> 2006203000 | Y18: =Y8-Y10 -> 2034031000 | AA18: =AA8-AA10 -> -130000 | AB18: =AB8-AB10 -> 7544000 | AD18: =AD8-AD10 -> 1136640775 | AE18: =AE8-AE10 -> 834016659 | AG18: =AG8-AG10 -> 12238571 | AH18: =AH8-AH10 -> 22027200
A20: Gross Margin | B20: =B18/B8 -> 0.13694083 | C20: =C18/C8 -> 0.1218194 | D20: =D18/D8 -> 0.14029394 | E20: =E18/E8 -> 0.88081278 | F20: =F18/F8 -> 0.0034582592 | G20: =G18/G8 -> 0.0042030406 | I20: =I18/I8 -> 0.07652366 | J20: =J18/J8 -> 0.058410958 | L20: =L18/L8 -> 0.13795373 | M20: =M18/M8 -> 0.094675019 | O20: =O18/O8 -> 0.14694924 | P20: =P18/P8 -> 0.1125781 | R20: =R18/R8 -> 0.04409618 | S20: =S18/S8 -> 0.040585146 | U20: =U18/U8 -> 0.069194556 | V20: =V18/V8 -> 0.055229275 | X20: =X18/X8 -> 0.1039886 | Y20: =Y18/Y8 -> 0.081692093 | AA20: =AA18/AA8 -> -0.00018761916 | AB20: =AB18/AB8 -> 0.024708503 | AD20: =AD18/AD8 -> 0.042001997 | AE20: =AE18/AE8 -> 0.040525916 | AG20: =AG18/AG8 -> 0.016850295 | AH20: =AH18/AH8 -> 0.033880208
A22: Weighted Average | B22: =SUM(B18:D18)/SUM(B8:D8) -> 0.13353124 | E22: =SUM(E18:G18)/SUM(E8:G8) -> 0.31223599 | H22: =SUM(H18:J18)/SUM(H8:J8) -> 0.066851697 | K22: =SUM(K18:M18)/SUM(K8:M8) -> 0.10965111 | N22: =SUM(N18:P18)/SUM(N8:P8) -> 0.13219929 | Q22: =SUM(Q18:S18)/SUM(Q8:S8) -> 0.04240355 | T22: =SUM(T18:V18)/SUM(T8:V8) -> 0.062399181 | W22: =SUM(W18:Y18)/SUM(W8:Y8) -> 0.091426048 | Z22: =SUM(Z18:AB18)/SUM(Z8:AB8) -> 0.0074272725 | AC22: =SUM(AC18:AE18)/SUM(AC8:AE8) -> 0.041364369 | AF22: =SUM(AF18:AH18)/SUM(AF8:AH8) -> 0.024894101

Sheet Payable Computation
B2: Payables Computation | X2: 0.693 | Y2: 0.6648 | Z2: 0.6232
B4: Particulars | C4: Astute Systems Private Limited | G4: Datasoft Network Solutions Private Limited | K4: Galaxy Office Automation Private Limited | O4: Informatics Technologies Private Limited | S4: Sonata Information Technology Limited | W4: NTT India Private Limited | AA4: Softcell Technologies Global Private Limited | AE4: Team Computers Private Limited | AI4: Avance Technologies Limited | AM4: Iris Global Services Private Limited | AQ4: Perfect Computer Solutions Private Limited
C6: FY 2025 | D6: FY 2024 | E6: FY 2023 | F6: FY 2022 | G6: FY 2025 | H6: FY 2024 | I6: FY 2023 | J6: FY 2022 | K6: FY 2025 | L6: FY 2024 | M6: FY 2023 | N6: FY 2022 | O6: FY 2025 | P6: FY 2024 | Q6: FY 2023 | R6: FY 2022 | S6: FY 2025 | T6: FY 2024 | U6: FY 2023 | V6: FY 2022 | W6: FY 2025 | X6: FY 2024 | Y6: FY 2023 | Z6: FY 2022 | AA6: FY 2025 | AB6: FY 2024 | AC6: FY 2023 | AD6: FY 2022 | AE6: FY 2025 | AF6: FY 2024 | AG6: FY 2023 | AH6: FY 2022 | AI6: FY 2025 | AJ6: FY 2024 | AK6: FY 2023 | AL6: FY 2022 | AM6: FY 2025 | AN6: FY 2024 | AO6: FY 2023 | AP6: FY 2022 | AQ6: FY 2025 | AR6: FY 2024 | AS6: FY 2023 | AT6: FY 2022
B7: Trade payables | C7: NA | D7: =11611*1000 -> 11611000 | E7: =20875.16*1000 -> 20875160 | F7: =23598*1000 -> 23598000 | G7: NA | H7: 613981760 | I7: 236620021 | J7: 108951025 | K7: NA | L7: 1623846880 | M7: =(198+18264)*10^5 -> 1846200000 | N7: =15426.15*10^5 -> 1542615000 | O7: NA | P7: 34008000 | Q7: =25242*10^3 -> 25242000 | R7: 25060205 | S7: NA | T7: 13463000000 | U7: 10727200000 | V7: =87547*10^5 -> 8754700000 | W7: NA | X7: =(54414*10^5)*69.3% -> 3.7708902e+09 | Y7: =(49981*10^5)*66.48% -> 3.3227369e+09 | Z7: =(51584*10^5)*62.32% -> 3214714880 | AA7: NA | AB7: =22892.23*10^5 -> 2289223000 | AC7: =12425.69*10^5 -> 1242569000 | AD7: 838135756 | AE7: NA | AF7: 3994569000 | AG7: =26978.42*10^5 -> 2697842000 | AH7: =39023.17*10^5 -> 3902317000 | AI7: NA | AJ7: 551624000 | AK7: 629374000 | AL7: 556907000 | AM7: NA | AN7: 3446171403 | AO7: 2777857847 | AP7: 1854191148 | AQ7: NA | AR7: 122319694 | AS7: 92429200 | AT7: 68385883
B8: Trade Advances | C8: NA | G8: NA | K8: NA | L8: 4623507 | M8: =64*10^5 -> 6400000 | N8: =136.81*10^5 -> 13681000 | O8: NA | S8: NA | V8: =1340*10^5 -> 134000000 | W8: NA | AA8: NA | AE8: NA | AI8: NA | AM8: NA | AQ8: NA
B9: Advance from customers/Unearned Revenue/Advance Billing | C9: NA | D9: =38*1000 -> 38000 | G9: NA | H9: 2499050 | I9: 3586975 | J9: 3489221 | K9: NA | L9: 16772727 | M9: =(769)*10^5 -> 76900000 | N9: =115.47*10^5 -> 11547000 | O9: NA | S9: NA | T9: 53500000 | U9: =203 *10^5 -> 20300000 | V9: =339*10^5 -> 33900000 | W9: NA | X9: =((21459)*10^5)*69.3% -> 1487108700 | Y9: =((18368)*10^5)*66.48% -> 1221104640 | Z9: =(13150*10^5)*62.32% -> 819508000 | AA9: NA | AB9: =(3.08+ 56.53)*10^5 -> 5961000 | AC9: =164.44*10^5 -> 16444000 | AD9: 28783354 | AE9: NA | AF9: 151887000 | AG9: =(575.22+561.13)*10^5 -> 1.13635e+08 | AH9: =(997.44+321.73)*10^5 -> 131917000 | AI9: NA | AM9: NA | AQ9: NA
B10: Other Payables | C10: NA | G10: NA | K10: NA | O10: NA | S10: NA | W10: NA | AA10: NA | AE10: NA | AI10: NA | AM10: NA | AQ10: NA
B12: Payables | C12: =SUM(C7:C10) -> 0 | D12: =SUM(D7:D10) -> 11649000 | E12: =SUM(E7:E10) -> 20875160 | F12: =SUM(F7:F10) -> 23598000 | G12: =SUM(G7:G10) -> 0 | H12: =SUM(H7:H10) -> 616480810 | I12: =SUM(I7:I10) -> 240206996 | J12: =SUM(J7:J10) -> 112440246 | ... AT12: =SUM(AT7:AT10) -> 68385883
B13: Average payables | C13: =AVERAGE(C12:D12) -> 5824500 | D13: =AVERAGE(D12:E12) -> 16262080 | E13: =AVERAGE(E12:F12) -> 22236580 | G13: =AVERAGE(G12:H12) -> 308240405 | H13: =AVERAGE(H12:I12) -> 428343903 | I13: =AVERAGE(I12:J12) -> 176323621 | K13: =AVERAGE(K12:L12) -> 822621557 | L13: =AVERAGE(L12:M12) -> 1787371557 | M13: =AVERAGE(M12:N12) -> 1748671500 | O13: =AVERAGE(O12:P12) -> 17004000 | P13: =AVERAGE(P12:Q12) -> 29625000 | Q13: =AVERAGE(Q12:R12) -> 25151102 | S13: =AVERAGE(S12:T12) -> 6758250000 | T13: =AVERAGE(T12:U12) -> 12132000000 | U13: =AVERAGE(U12:V12) -> 9835050000 | W13: =AVERAGE(W12:X12) -> 2628999450 | X13: =AVERAGE(X12:Y12) -> 4900920210 | Y13: =AVERAGE(Y12:Z12) -> 4289032200 | AA13: =AVERAGE(AA12:AB12) -> 1147592000 | AB13: =AVERAGE(AB12:AC12) -> 1777098500 | AC13: =AVERAGE(AC12:AD12) -> 1062966055 | AE13: =AVERAGE(AE12:AF12) -> 2073228000 | AF13: =AVERAGE(AF12:AG12) -> 3478966500 | AG13: =AVERAGE(AG12:AH12) -> 3422855500 | AI13: =AVERAGE(AI12:AJ12) -> 275812000 | AJ13: =AVERAGE(AJ12:AK12) -> 590499000 | AK13: =AVERAGE(AK12:AL12) -> 593140500 | AM13: =AVERAGE(AM12:AN12) -> 1.7230857e+09 | AN13: =AVERAGE(AN12:AO12) -> 3112014625 | AO13: =AVERAGE(AO12:AP12) -> 2.3160245e+09 | AQ13: =AVERAGE(AQ12:AR12) -> 61159847 | AR13: =AVERAGE(AR12:AS12) -> 107374447 | AS13: =AVERAGE(AS12:AT12) -> 80407542

Sheet Avg Payable days
B1: Payables considered comparable for the transfer pricing analysis of XYZ India Private Limited
B3: Particulars | C3: Astute Systems Private Limited | F3: Datasoft Network Solutions Private Limited | I3: Galaxy Office Automation Private Limited | L3: Informatics Technologies Private Limited | O3: NTT India Private Limited | R3: Sonata Information Technology Limited | U3: Softcell Technologies Global Private Limited | X3: Team Computers Private Limited | AA3: Avance Technologies Limited | AD3: Iris Global Services Private Limited | AG3: Perfect Computer Solutions Private Limited
C4: FY 2025 | D4: FY 2024 | E4: FY 2023 | F4: FY 2025 | G4: FY 2024 | H4: FY 2023 | I4: FY 2025 | J4: FY 2024 | K4: FY 2023 | L4: FY 2025 | M4: FY 2024 | N4: FY 2023 | O4: FY 2025 | P4: FY 2024 | Q4: FY 2023 | R4: FY 2025 | S4: FY 2024 | T4: FY 2023 | U4: FY 2025 | V4: FY 2024 | W4: FY 2023 | X4: FY 2025 | Y4: FY 2024 | Z4: FY 2023 | AA4: FY 2025 | AB4: FY 2024 | AC4: FY 2023 | AD4: FY 2025 | AE4: FY 2024 | AF4: FY 2023 | AG4: FY 2025 | AH4: FY 2024 | AI4: FY 2023
B6: Total Cost | C6: NA | D6: =88729*1000 -> 88729000 | E6: =99166.89*1000 -> 99166890 | F6: NA | G6: =948686.24*1000 -> 948686240 | H6: 701378400 | I6: NA | J6: 7127379251 | K6: =81377*10^5 -> 8137700000 | L6: NA | M6: 217508000 | N6: =393515*10^3 -> 393515000 | O6: NA | P6: =193661*10^5 -> 19366100000 | Q6: =154994*10^5 -> 15499400000 | R6: NA | S6: 57955300000 | T6: 53931600000 | U6: NA | V6: =88026.7*10^5 -> 8802670000 | W6: =84231.27*10^5 -> 8423127000 | X6: NA | Y6: 21660430000 | Z6: =271626.86*10^5 -> 27162686000 | AA6: NA | AB6: 695942000 | AC6: 300409000 | AD6: NA | AE6: 2.6434455e+10 | AF6: 20121629075 | AG6: NA | AH6: 752296281 | AI6: 666228600
B7: Total operating Cost | C7: NA | D7: 88699000 | E7: 99153180 | F7: NA | G7: 940649880 | H7: 694322810 | I7: NA | J7: 7108375061 | K7: 8122100000 | L7: NA | M7: 216590000 | N7: 392102000 | O7: NA | P7: =190962*10^5 -> 19096200000 | Q7: 15028400000 | R7: NA | S7: 57877500000 | T7: 53871700000 | U7: NA | V7: =87871.73*10^5 -> 8787173000 | W7: =(84231.27-251.38-29.33)*10^5 -> 8395056000 | X7: NA | Y7: 21572727000 | Z7: 27105757000 | AA7: NA | AB7: 694867000 | AC7: 299463000 | AD7: NA | AE7: 2.627131e+10 | AF7: 20014384135 | AG7: NA | AH7: 747672695 | AI7: 662665853
B8: Operating Cost/ Total cost | D8: =D7/D6 -> 0.99966189 | E8: =E7/E6 -> 0.99986175 | G8: =G7/G6 -> 0.99152896 | H8: =H7/H6 -> 0.98994039 | J8: =J7/J6 -> 0.99733364 | K8: =K7/K6 -> 0.998083 | M8: =M7/M6 -> 0.99577947 | N8: =N7/N6 -> 0.99640929 | P8: =P7/P6 -> 0.98606328 | Q8: =Q7/Q6 -> 0.96961173 | S8: =S7/S6 -> 0.99865759 | T8: =T7/T6 -> 0.99888933 | V8: =V7/V6 -> 0.99823951 | W8: =W7/W6 -> 0.99666739 | Y8: =Y7/Y6 -> 0.995951 | Z8: =Z7/Z6 -> 0.99790415 | AB8: =AB7/AB6 -> 0.99845533 | AC8: =AC7/AC6 -> 0.99685096 | AE8: =AE7/AE6 -> 0.9938283 | AF8: =AF7/AF6 -> 0.99467017 | AH8: =AH7/AH6 -> 0.99385404 | AI8: =AI7/AI6 -> 0.99465237
B9: Cost of Goods Sold ("COGS") | D9: ='Gross Margins'!C10 -> 78927360 | E9: ='Gross Margins'!D10 -> 89678020 | G9: ='Gross Margins'!F10 -> 886480193 | H9: ='Gross Margins'!G10 -> 645903970 | J9: ='Gross Margins'!I10 -> 6584120604 | K9: ='Gross Margins'!J10 -> 7692500000 | M9: ='Gross Margins'!L10 -> 180728000 | N9: ='Gross Margins'!M10 -> 358697000 | P9: ='Gross Margins'!O10 -> 11242100000 | Q9: ='Gross Margins'!P10 -> 8791600000 | S9: ='Gross Margins'!R10 -> 56841100000 | T9: ='Gross Margins'!S10 -> 53103900000 | V9: ='Gross Margins'!U10 -> 7662813000 | W9: ='Gross Margins'!V10 -> 7371498000 | Y9: ='Gross Margins'!X10 -> 17286326000 | Z9: ='Gross Margins'!Y10 -> 22864719000 | AB9: ='Gross Margins'!AA10 -> 693023000 | AC9: ='Gross Margins'!AB10 -> 297776000 | AE9: ='Gross Margins'!AD10 -> 25924947914 | AF9: ='Gross Margins'!AE10 -> 19745818019 | AH9: ='Gross Margins'!AG10 -> 714073416 | AI9: ='Gross Margins'!AH10 -> 628122300
B10: COGS/Total Cost | D10: =D9/D6 -> 0.88953285 | E10: =E9/E6 -> 0.90431413 | G10: =G9/G6 -> 0.93442927 | H10: =H9/H6 -> 0.92090656 | J10: =J9/J6 -> 0.92377862 | K10: =K9/K6 -> 0.94529167 | M10: =M9/M6 -> 0.83090277 | N10: =N9/N6 -> 0.91152053 | P10: =P9/P6 -> 0.58050408 | Q10: =Q9/Q6 -> 0.56722196 | S10: =S9/S6 -> 0.98077484 | T10: =T9/T6 -> 0.98465278 | V10: =V9/V6 -> 0.87051008 | W10: =W9/W6 -> 0.87514981 | Y10: =Y9/Y6 -> 0.79806015 | Z10: =Z9/Z6 -> 0.84176944 | AB10: =AB9/AB6 -> 0.99580568 | AC10: =AC9/AC6 -> 0.99123528 | AE10: =AE9/AE6 -> 0.98072565 | AF10: =AF9/AF6 -> 0.98132303 | AH10: =AH9/AH6 -> 0.94919174 | AI10: =AI9/AI6 -> 0.94280297
B12: Average payables for comparable companies w.r.t. Operating Cost | C12: NA | D12: ='Payable Computation'!D13*D8 -> 16256582 | E12: ='Payable Computation'!E13*E8 -> 22233506 | F12: NA | G12: ='Payable Computation'!H13*G8 -> 4.2471538e+08 | H12: ='Payable Computation'!I13*H8 -> 1.7454987e+08 | I12: NA | J12: ='Payable Computation'!L13*'Avg Payable days'!J8 -> 1.7826058e+09 | K12: ='Payable Computation'!M13*'Avg Payable days'!K8 -> 1.7453193e+09 | L12: NA | M12: ='Payable Computation'!P13*'Avg Payable days'!M8 -> 29499967 | N12: ='Payable Computation'!Q13*'Avg Payable days'!N8 -> 25060792 | O12: NA | P12: ='Payable Computation'!X13*'Avg Payable days'!P8 -> 4.8326174e+09 | Q12: ='Payable Computation'!Y13*'Avg Payable days'!Q8 -> 4.1586959e+09 | R12: NA | S12: ='Payable Computation'!T13*'Avg Payable days'!S8 -> 1.2115714e+10 | T12: ='Payable Computation'!U13*'Avg Payable days'!T8 -> 9.8241265e+09 | U12: NA | V12: ='Payable Computation'!AB13*V8 -> 1.7739699e+09 | W12: ='Payable Computation'!AC13*W8 -> 1.0594236e+09 | X12: NA | Y12: ='Payable Computation'!AF13*Y8 -> 3.4648802e+09 | Z12: ='Payable Computation'!AG13*Z8 -> 3.4156817e+09 | AA12: NA | AB12: ='Payable Computation'!AJ13*AB8 -> 5.8958687e+08 | AC12: ='Payable Computation'!AK13*AC8 -> 5.9127268e+08 | AD12: NA | AE12: ='Payable Computation'!AN13*AE8 -> 3.0928082e+09 | AF12: ='Payable Computation'!AO13*AF8 -> 2.3036805e+09 | AG12: NA | AH12: ='Payable Computation'!AR13*AH8 -> 1.0671453e+08 | AI12: ='Payable Computation'!AS13*AI8 -> 79977551
B13: Average payables for comparable companies w.r.t. COGS | C13: NA | D13: ='Payable Computation'!D13*D10 -> 14465654 | E13: ='Payable Computation'!E13*E10 -> 20108854 | F13: NA | G13: ='Payable Computation'!H13*G10 -> 4.0025708e+08 | H13: ='Payable Computation'!I13*H10 -> 1.6237758e+08 | I13: NA | J13: ='Payable Computation'!L13*'Avg Payable days'!J10 -> 1.6511356e+09 | K13: ='Payable Computation'!M13*'Avg Payable days'!K10 -> 1.6530046e+09 | L13: NA | M13: ='Payable Computation'!P13*'Avg Payable days'!M10 -> 24615495 | N13: ='Payable Computation'!Q13*'Avg Payable days'!N10 -> 22925746 | O13: NA | P13: ='Payable Computation'!X13*'Avg Payable days'!P10 -> 2.8450042e+09 | Q13: ='Payable Computation'!Y13*'Avg Payable days'!Q10 -> 2.4328332e+09 | R13: NA | S13: ='Payable Computation'!T13*'Avg Payable days'!S10 -> 1.189876e+10 | T13: ='Payable Computation'!U13*'Avg Payable days'!T10 -> 9.6841093e+09 | U13: NA | V13: ='Payable Computation'!AB13*V10 -> 1.5469822e+09 | W13: ='Payable Computation'!AC13*W10 -> 9.3025454e+08 | X13: NA | Y13: ='Payable Computation'!AF13*Y10 -> 2.7764245e+09 | Z13: ='Payable Computation'!AG13*Z10 -> 2.8812552e+09 | AA13: NA | AB13: ='Payable Computation'!AJ13*AB10 -> 5.8802226e+08 | AC13: ='Payable Computation'!AK13*AC10 -> 5.8794179e+08 | AD13: NA | AE13: ='Payable Computation'!AN13*AE10 -> 3.0520326e+09 | AF13: ='Payable Computation'!AO13*AF10 -> 2.2727682e+09 | AG13: NA | AH13: ='Payable Computation'!AR13*AH10 -> 1.0191894e+08 | AI13: ='Payable Computation'!AS13*AI10 -> 75808469
B15: Payables as a percentage cost (Comparables) | C15: NA | D15: =D12/D7 -> 0.18327807 | E15: =E12/E7 -> 0.22423392 | F15: NA | G15: =G12/G7 -> 0.45151272 | H15: =H12/H7 -> 0.25139585 | I15: NA | J15: =J12/J7 -> 0.25077542 | K15: =K12/K7 -> 0.21488523 | L15: NA | M15: =M12/M7 -> 0.13620189 | N15: =N12/N7 -> 0.063913961 | O15: NA | P15: =P12/P7 -> 0.25306697 | Q15: =Q12/Q7 -> 0.27672247 | R15: NA | S15: =S12/S7 -> 0.20933375 | T15: =T12/T7 -> 0.18236155 | U15: NA | V15: =V12/V7 -> 0.20188176 | W15: =W12/W7 -> 0.12619613 | X15: NA | Y15: =Y12/Y7 -> 0.16061392 | Z15: =Z12/Z7 -> 0.12601315 | AA15: NA | AB15: =AB12/AB7 -> 0.84848881 | AC15: =AC12/AC7 -> 1.9744432 | AD15: NA | AE15: =AE12/AE7 -> 0.1177257 | AF15: =AF12/AF7 -> 0.11510124 | AG15: NA | AH15: =AH12/AH7 -> 0.14272894 | AI15: =AI12/AI7 -> 0.12069062
B16: Average payable days (Comparables) | C16: NA | D16: =(D12/D7)*365 -> 66.896496 | E16: =(E12/E7)*365 -> 81.845379 | F16: NA | G16: =(G12/G7)*365 -> 164.80214 | H16: =(H12/H7)*365 -> 91.759486 | I16: NA | J16: =(J12/J7)*365 -> 91.53303 | K16: =(K12/K7)*365 -> 78.433107 | L16: NA | M16: =(M12/M7)*365 -> 49.713689 | N16: =(N12/N7)*365 -> 23.328596 | O16: NA | P16: =(P12/P7)*365 -> 92.369443 | Q16: =(Q12/Q7)*365 -> 101.0037 | R16: NA | S16: =(S12/S7)*365 -> 76.406817 | T16: =(T12/T7)*365 -> 66.561965 | U16: NA | V16: =(V12/V7)*365 -> 73.686842 | W16: =(W12/W7)*365 -> 46.061589 | X16: NA | Y16: =(Y12/Y7)*365 -> 58.62408 | Z16: =(Z12/Z7)*365 -> 45.994798 | AA16: NA | AB16: =(AB12/AB7)*365 -> 309.69842 | AC16: =(AC12/AC7)*365 -> 720.67176 | AD16: NA | AE16: =(AE12/AE7)*365 -> 42.969879 | AF16: =(AF12/AF7)*365 -> 42.011953 | AG16: NA | AH16: =(AH12/AH7)*365 -> 52.096061 | AI16: =(AI12/AI7)*365 -> 44.052076
B17: Weighted average | C17: =SUM(C12:E12)/SUM(C7:E7)*365 -> 74.786898 | F17: =SUM(F12:H12)/SUM(F7:H7)*365 -> 133.78316 | I17: =SUM(I12:K12)/SUM(I7:K7)*365 -> 84.54711 | L17: =SUM(L12:N12)/SUM(L7:N7)*365 -> 32.717166 | O17: =SUM(O12:Q12)/SUM(O7:Q7)*365 -> 96.171951 | R17: =SUM(R12:T12)/SUM(R7:T7)*365 -> 71.660842 | X17: =SUM(X12:Z12)/SUM(X7:Z7)*365 -> 51.591686 | AA17: =SUM(AA12:AC12)/SUM(AA7:AC7)*365 -> 433.47152 | AD17: =SUM(AD12:AF12)/SUM(AD7:AF7)*365 -> 42.555663 | AG17: =SUM(AG12:AI12)/SUM(AG7:AI7)*365 -> 48.31649
B18: Arithmetic Mean w.r.t. operating cost | C18: =AVERAGE(C17:AI17) -> 106.96025
B19: Average payable days (Comparables) | D19: =(D13/D9)*365 -> 66.896496 | E19: =(E13/E9)*365 -> 81.845379 | G19: =(G13/G9)*365 -> 164.80214 | H19: =(H13/H9)*365 -> 91.759486 | J19: =(J13/J9)*365 -> 91.53303 | K19: =(K13/K9)*365 -> 78.433107 | M19: =(M13/M9)*365 -> 49.713689 | N19: =(N13/N9)*365 -> 23.328596 | P19: =(P13/P9)*365 -> 92.369443 | Q19: =(Q13/Q9)*365 -> 101.0037 | S19: =(S13/S9)*365 -> 76.406817 | T19: =(T13/T9)*365 -> 66.561965 | V19: =(V13/V9)*365 -> 73.686842 | W19: =(W13/W9)*365 -> 46.061589 | Y19: =(Y13/Y9)*365 -> 58.62408 | Z19: =(Z13/Z9)*365 -> 45.994798 | AB19: =(AB13/AB9)*365 -> 309.69842 | AC19: =(AC13/AC9)*365 -> 720.67176 | AE19: =(AE13/AE9)*365 -> 42.969879 | AF19: =(AF13/AF9)*365 -> 42.011953 | AH19: =(AH13/AH9)*365 -> 52.096061 | AI19: =(AI13/AI9)*365 -> 44.052076
B20: Weighted average | C20: =SUM(C13:E13)/SUM(C9:E9)*365 -> 74.847525 | F20: =SUM(F13:H13)/SUM(F9:H9)*365 -> 134.01447 | I20: =SUM(I13:K13)/SUM(I9:K9)*365 -> 84.474556 | L20: =SUM(L13:N13)/SUM(L9:N9)*365 -> 32.168611 | O20: =SUM(O13:Q13)/SUM(O9:Q9)*365 -> 96.158505 | R20: =SUM(R13:T13)/SUM(R9:T9)*365 -> 71.651712 | U20: =SUM(U13:W13)/SUM(U9:W9)*365 -> 60.141858 | X20: =SUM(X13:Z13)/SUM(X9:Z9)*365 -> 51.432113 | AA20: =SUM(AA13:AC13)/SUM(AA9:AC9)*365 -> 433.21287 | AD20: =SUM(AD13:AF13)/SUM(AD9:AF9)*365 -> 42.555719 | AG20: =SUM(AG13:AI13)/SUM(AG9:AI9)*365 -> 48.331628
B21: Arithmetic Mean w.r.t COGS | C21: =AVERAGE(C20:AI20) -> 102.63542 | D21: =AVERAGE(C20:AI20) -> 102.63542
B23: NA denotes Not available
